Metadata-Version: 2.1
Name: pyplazmix
Version: 0.1.1
Summary: A python wrapper for PlazmixAPI
Home-page: https://github.com/TheStngularity/pyplazmix
Author: The Singularity
License: UNKNOWN
Platform: UNKNOWN
Classifier: Programming Language :: Python :: 3.9
Requires-Python: >=3.9.0
